{"errors":[],"warnings":[],"version":"1.13.3","hash":"2bc9edaf9c4695a30726","publicPath":"/","assetsByChunkName":{"main":"main.min.js"},"assets":[{"name":"main.min.js","size":629523,"chunks":[0],"chunkNames":["main"],"emitted":true},{"name":"webpack.stats.json","size":0,"chunks":[],"chunkNames":[]}],"chunks":[{"id":0,"rendered":true,"initial":true,"entry":true,"extraAsync":false,"size":1805247,"names":["main"],"files":["main.min.js"],"hash":"c0dce83ef21a679dc739","parents":[],"origins":[{"moduleId":0,"module":"multi main","moduleIdentifier":"multi main","moduleName":"multi main","loc":"","name":"main","reasons":[]}]}],"children":[]}